{
  "version": "1.0",
  "created_at": "2026-03-01",
  "source_papers": 361,
  "description": "电商论文属性库 - 从361篇论文中提取的问题、解法、数据集、指标等属性",
  "problem_types": {
    "retrieval": {"count": 278, "description": "信息检索，从大规模相关项目集合中找到目标"},
    "evaluation": {"count": 223, "description": "评估方法，设计指标衡量系统效果"},
    "accuracy": {"count": 211, "description": "准确率优化，提升预测/匹配精度"},
    "recommendation": {"count": 204, "description": "推荐系统，为用户推荐感兴趣项目"},
    "matching": {"count": 201, "description": "匹配/对齐，建立项目间的对应关系"},
    "prediction": {"count": 164, "description": "预测任务，预测用户行为或项目属性"},
    "generation": {"count": 164, "description": "内容生成，生成文本/图像等内容"},
    "ranking": {"count": 135, "description": "排序优化，对候选项目进行排序"},
    "noise": {"count": 115, "description": "噪声处理，提升系统鲁棒性"},
    "efficiency": {"count": 108, "description": "效率优化，提升计算效率或可扩展性"},
    "classification": {"count": 98, "description": "分类任务，将项目分类到预定义类别"},
    "fairness": {"count": 96, "description": "公平性，确保推荐/分配的公平"},
    "explainability": {"count": 63, "description": "可解释性，让用户理解系统决策原因"},
    "personalization": {"count": 54, "description": "个性化，针对个人用户定制"},
    "sparsity": {"count": 54, "description": "稀疏性问题，数据稀疏导致的问题"},
    "cold_start": {"count": 39, "description": "冷启动，新用户/新项目缺乏历史数据"}
  },
  "solution_methods": {
    "reinforcement": {"count": 230, "description": "强化学习，RL、Bandit、Policy Gradient"},
    "transformer": {"count": 216, "description": "Transformer架构，BERT、GPT、Attention"},
    "embedding": {"count": 206, "description": "向量化表示，将实体映射到向量空间"},
    "graph": {"count": 109, "description": "图方法，GNN、GCN、知识图谱"},
    "neural_network": {"count": 86, "description": "神经网络，CNN、RNN、LSTM、GRU"},
    "transfer_learning": {"count": 73, "description": "迁移学习，预训练+微调"},
    "gan": {"count": 56, "description": "生成对抗网络"},
    "metric_learning": {"count": 47, "description": "度量学习，Siamese、Triplet、Contrastive"},
    "cnn": {"count": 22, "description": "卷积神经网络"},
    "ensemble": {"count": 21, "description": "集成学习，Boosting、Bagging"},
    "rnn": {"count": 20, "description": "循环神经网络"},
    "vae": {"count": 7, "description": "变分自编码器"}
  },
  "datasets": {
    "amazon": {"count": 54, "type": "电商", "description": "Amazon电商数据集"},
    "movielens": {"count": 23, "type": "推荐", "description": "MovieLens电影推荐数据集"},
    "taobao": {"count": 22, "type": "电商", "description": "淘宝电商数据集"},
    "yelp": {"count": 14, "type": "评论", "description": "Yelp商家评论数据集"},
    "ebay": {"count": 9, "type": "电商", "description": "eBay电商数据集"},
    "jd": {"count": 7, "type": "电商", "description": "京东电商数据集"},
    "twitter": {"count": 5, "type": "社交", "description": "Twitter社交数据集"},
    "netflix": {"count": 4, "type": "推荐", "description": "Netflix电影推荐数据集"},
    "douban": {"count": 3, "type": "评论", "description": "豆瓣数据集"},
    "pinterest": {"count": 3, "type": "社交", "description": "Pinterest社交数据集"},
    "aliexpress": {"count": 2, "type": "电商", "description": "速卖通电商数据集"},
    "beir": {"count": 2, "type": "检索", "description": "BEIR信息检索基准"},
    "tmall": {"count": 1, "type": "电商", "description": "天猫电商数据集"}
  },
  "metrics": {
    "accuracy": {"count": 146, "type": "分类", "description": "准确率"},
    "recall": {"count": 95, "type": "检索", "description": "召回率"},
    "loss": {"count": 81, "type": "训练", "description": "损失值"},
    "map": {"count": 71, "type": "检索", "description": "平均精度均值"},
    "precision": {"count": 71, "type": "分类", "description": "精确率"},
    "f1": {"count": 61, "type": "分类", "description": "F1分数"},
    "ctr": {"count": 61, "type": "转化", "description": "点击率"},
    "ndcg": {"count": 59, "type": "排序", "description": "归一化折损累积增益"},
    "conversion": {"count": 41, "type": "转化", "description": "转化率"},
    "auc": {"count": 40, "type": "分类", "description": "曲线下面积"},
    "mrr": {"count": 27, "type": "检索", "description": "平均倒数排名"},
    "bleu": {"count": 26, "type": "生成", "description": "BLEU分数"},
    "cvr": {"count": 23, "type": "转化", "description": "转化率"},
    "rmse": {"count": 17, "type": "回归", "description": "均方根误差"},
    "roi": {"count": 14, "type": "商业", "description": "投资回报率"},
    "mae": {"count": 14, "type": "回归", "description": "平均绝对误差"},
    "rouge": {"count": 10, "type": "生成", "description": "ROUGE分数"},
    "hit_rate": {"count": 5, "type": "推荐", "description": "命中率"},
    "perplexity": {"count": 3, "type": "语言", "description": "困惑度"}
  },
  "categories": {
    "product_matching": {"count": 160, "description": "商品匹配，商品与Query/商品的匹配"},
    "ecommerce_evaluation": {"count": 106, "description": "电商评测，推荐/搜索系统效果评估"},
    "mini_program_service": {"count": 94, "description": "小程序服务，API发现与组合"},
    "unknown": {"count": 1, "description": "未知分类"}
  },
  "statistics": {
    "total_problems": 16,
    "total_solutions": 12,
    "total_datasets": 13,
    "total_metrics": 19,
    "total_categories": 4
  }
}
